{"capacityMeshNodeId":"sample-007744","center":{"x":0,"y":0},"width":1.02,"height":2.74,"availableZ":[0,1],"portPoints":[{"connectionName":"conn00","rootConnectionName":"root00","portPointId":"conn00-a","x":-0.37,"y":1.36,"z":1},{"connectionName":"conn00","rootConnectionName":"root00","portPointId":"conn00-b","x":-0.05,"y":-1.36,"z":1},{"connectionName":"conn01","rootConnectionName":"root01","portPointId":"conn01-a","x":0.5,"y":-0.24,"z":0},{"connectionName":"conn01","rootConnectionName":"root01","portPointId":"conn01-b","x":-0.05,"y":-1.36,"z":0}],"solvable":true,"solution":[{"connectionName":"conn01","traceThickness":0.1,"viaDiameter":0.3,"route":[{"x":0.51,"y":-0.21,"z":0},{"x":0.4,"y":-0.32,"z":0},{"x":0.28,"y":-0.42,"z":0},{"x":0.17,"y":-0.53,"z":0},{"x":0.06,"y":-0.63,"z":0},{"x":-0.06,"y":-0.74,"z":0},{"x":-0.06,"y":-0.84,"z":0},{"x":-0.06,"y":-0.95,"z":0},{"x":-0.06,"y":-1.05,"z":0},{"x":-0.06,"y":-1.16,"z":0},{"x":-0.06,"y":-1.26,"z":0},{"x":-0.06,"y":-1.37,"z":0}],"vias":[],"rootConnectionName":"root01"},{"connectionName":"conn00","traceThickness":0.1,"viaDiameter":0.3,"route":[{"x":-0.4,"y":1.37,"z":1},{"x":-0.28,"y":1.26,"z":1},{"x":-0.17,"y":1.16,"z":1},{"x":-0.06,"y":1.05,"z":1},{"x":-0.06,"y":0.95,"z":1},{"x":-0.06,"y":0.84,"z":1},{"x":-0.06,"y":0.74,"z":1},{"x":-0.06,"y":0.63,"z":1},{"x":-0.06,"y":0.53,"z":1},{"x":-0.06,"y":0.42,"z":1},{"x":-0.06,"y":0.32,"z":1},{"x":-0.06,"y":0.21,"z":1},{"x":-0.06,"y":0.11,"z":1},{"x":-0.06,"y":0,"z":1},{"x":-0.06,"y":-0.11,"z":1},{"x":-0.06,"y":-0.21,"z":1},{"x":-0.06,"y":-0.32,"z":1},{"x":-0.06,"y":-0.42,"z":1},{"x":-0.06,"y":-0.53,"z":1},{"x":-0.06,"y":-0.63,"z":1},{"x":-0.06,"y":-0.74,"z":1},{"x":-0.06,"y":-0.84,"z":1},{"x":-0.06,"y":-0.95,"z":1},{"x":-0.06,"y":-1.05,"z":1},{"x":-0.06,"y":-1.16,"z":1},{"x":-0.06,"y":-1.26,"z":1},{"x":-0.06,"y":-1.37,"z":1}],"vias":[],"rootConnectionName":"root00"}]}
