{
  "capacityMeshNodeId": "sample-000064",
  "center": {
    "x": 0.00,
    "y": 0.00
  },
  "width": 1.02,
  "height": 2.44,
  "availableZ": [
    0.00,
    1.00
  ],
  "portPoints": [
    {
      "connectionName": "conn00",
      "rootConnectionName": "root00",
      "portPointId": "conn00-a",
      "x": 0.50,
      "y": -0.06,
      "z": 0.00
    },
    {
      "connectionName": "conn00",
      "rootConnectionName": "root00",
      "portPointId": "conn00-b",
      "x": -0.50,
      "y": -0.20,
      "z": 0.00
    },
    {
      "connectionName": "conn01",
      "rootConnectionName": "root01",
      "portPointId": "conn01-a",
      "x": -0.11,
      "y": -1.22,
      "z": 0.00
    },
    {
      "connectionName": "conn01",
      "rootConnectionName": "root01",
      "portPointId": "conn01-b",
      "x": -0.13,
      "y": 1.22,
      "z": 0.00
    },
    {
      "connectionName": "conn02",
      "rootConnectionName": "root02",
      "portPointId": "conn02-a",
      "x": -0.50,
      "y": 0.14,
      "z": 1.00
    },
    {
      "connectionName": "conn02",
      "rootConnectionName": "root02",
      "portPointId": "conn02-b",
      "x": 0.50,
      "y": 0.69,
      "z": 0.00
    }
  ],
  "solvable": true
}
