{"capacityMeshNodeId":"sample-011531","center":{"x":0,"y":0},"width":1.08,"height":2.18,"availableZ":[0,1],"portPoints":[{"connectionName":"conn00","rootConnectionName":"root00","portPointId":"conn00-a","x":0.2,"y":-1.09,"z":1},{"connectionName":"conn00","rootConnectionName":"root00","portPointId":"conn00-b","x":-0.55,"y":-0.62,"z":0},{"connectionName":"conn01","rootConnectionName":"root01","portPointId":"conn01-a","x":0.22,"y":-1.09,"z":0},{"connectionName":"conn01","rootConnectionName":"root01","portPointId":"conn01-b","x":0.55,"y":-0.05,"z":0},{"connectionName":"conn02","rootConnectionName":"root02","portPointId":"conn02-a","x":-0.05,"y":1.09,"z":0},{"connectionName":"conn02","rootConnectionName":"root02","portPointId":"conn02-b","x":-0.22,"y":-1.09,"z":0}],"solvable":true,"solution":[{"connectionName":"conn00","traceThickness":0.1,"viaDiameter":0.3,"route":[{"connectionName":"conn00","rootConnectionName":"root00","portPointId":"conn00-a","x":0.2,"y":-1.09,"z":1},{"x":0.11,"y":-1.09,"z":1},{"x":0.01,"y":-1.09,"z":1},{"x":-0.1,"y":-1.09,"z":1},{"x":-0.21,"y":-1.09,"z":1},{"x":-0.21,"y":-0.99,"z":1},{"x":-0.32,"y":-0.99,"z":1},{"x":-0.32,"y":-0.88,"z":1},{"x":-0.43,"y":-0.88,"z":1},{"x":-0.43,"y":-0.78,"z":1},{"x":-0.43,"y":-0.67,"z":1},{"x":-0.43,"y":-0.67,"z":0},{"connectionName":"conn00","rootConnectionName":"root00","portPointId":"conn00-b","x":-0.55,"y":-0.62,"z":0}],"vias":[{"x":-0.43,"y":-0.67}],"rootConnectionName":"root00"},{"connectionName":"conn01","traceThickness":0.1,"viaDiameter":0.3,"route":[{"connectionName":"conn01","rootConnectionName":"root01","portPointId":"conn01-a","x":0.22,"y":-1.09,"z":0},{"x":0.22,"y":-0.99,"z":0},{"x":0.22,"y":-0.88,"z":0},{"x":0.22,"y":-0.78,"z":0},{"x":0.22,"y":-0.67,"z":0},{"x":0.22,"y":-0.57,"z":0},{"x":0.22,"y":-0.46,"z":0},{"x":0.22,"y":-0.36,"z":0},{"x":0.22,"y":-0.26,"z":0},{"x":0.33,"y":-0.26,"z":0},{"x":0.33,"y":-0.15,"z":0},{"x":0.44,"y":-0.15,"z":0},{"x":0.44,"y":-0.05,"z":0},{"connectionName":"conn01","rootConnectionName":"root01","portPointId":"conn01-b","x":0.55,"y":-0.05,"z":0}],"vias":[],"rootConnectionName":"root01"},{"connectionName":"conn02","traceThickness":0.1,"viaDiameter":0.3,"route":[{"connectionName":"conn02","rootConnectionName":"root02","portPointId":"conn02-a","x":-0.05,"y":1.09,"z":0},{"x":0.01,"y":1.09,"z":0},{"x":0.01,"y":1,"z":0},{"x":0.01,"y":0.89,"z":0},{"x":0.01,"y":0.79,"z":0},{"x":0.01,"y":0.68,"z":0},{"x":0.01,"y":0.58,"z":0},{"x":0.01,"y":0.47,"z":0},{"x":0.01,"y":0.37,"z":0},{"x":0.01,"y":0.21,"z":0},{"x":0.01,"y":-0.1,"z":0},{"x":0.01,"y":-0.36,"z":0},{"x":0.01,"y":-0.46,"z":0},{"x":0.01,"y":-0.57,"z":0},{"x":0.01,"y":-0.67,"z":0},{"x":0.01,"y":-0.78,"z":0},{"x":0.01,"y":-0.88,"z":0},{"x":0.01,"y":-0.99,"z":0},{"x":0.01,"y":-1.09,"z":0},{"x":-0.1,"y":-1.09,"z":0},{"connectionName":"conn02","rootConnectionName":"root02","portPointId":"conn02-b","x":-0.22,"y":-1.09,"z":0}],"vias":[],"rootConnectionName":"root02"}]}
