{"capacityMeshNodeId":"sample-007378","center":{"x":0,"y":0},"width":2.92,"height":1.03,"availableZ":[0,1],"portPoints":[{"connectionName":"conn00","rootConnectionName":"root00","portPointId":"conn00-a","x":-0.55,"y":0.5,"z":0},{"connectionName":"conn00","rootConnectionName":"root00","portPointId":"conn00-b","x":0.84,"y":0.5,"z":0}],"solvable":true,"solution":[{"connectionName":"conn00","route":[{"x":-0.55,"y":0.5,"z":0},{"x":-0.41,"y":0.46,"z":0},{"x":-0.27,"y":0.45,"z":0},{"x":-0.13,"y":0.45,"z":0},{"x":0.01,"y":0.45,"z":0},{"x":0.14,"y":0.45,"z":0},{"x":0.28,"y":0.45,"z":0},{"x":0.42,"y":0.45,"z":0},{"x":0.56,"y":0.45,"z":0},{"x":0.7,"y":0.46,"z":0},{"x":0.84,"y":0.5,"z":0}],"traceThickness":0.1,"viaDiameter":0.3,"vias":[],"rootConnectionName":"root00"}],"vecRaw":[2.83,2.4,0.54]}
