{"capacityMeshNodeId":"sample-008499","center":{"x":0,"y":0},"width":1.03,"height":1.06,"availableZ":[0,1],"portPoints":[{"connectionName":"conn00","rootConnectionName":"root00","portPointId":"conn00-a","x":-0.52,"y":-0.11,"z":0},{"connectionName":"conn00","rootConnectionName":"root00","portPointId":"conn00-b","x":0.52,"y":0.41,"z":1},{"connectionName":"conn01","rootConnectionName":"root01","portPointId":"conn01-a","x":0.05,"y":0.53,"z":0},{"connectionName":"conn01","rootConnectionName":"root01","portPointId":"conn01-b","x":-0.14,"y":-0.53,"z":0}],"solvable":true,"solution":[{"connectionName":"conn00","traceThickness":0.1,"viaDiameter":0.3,"route":[{"x":-0.52,"y":-0.11,"z":0},{"x":-0.41,"y":-0.03,"z":0},{"x":-0.33,"y":0.04,"z":0},{"x":-0.22,"y":0.08,"z":0},{"x":-0.11,"y":0.1,"z":0},{"x":-0.11,"y":0.1,"z":1},{"x":0.01,"y":0.11,"z":1},{"x":0.12,"y":0.15,"z":1},{"x":0.21,"y":0.22,"z":1},{"x":0.31,"y":0.29,"z":1},{"x":0.41,"y":0.35,"z":1},{"x":0.52,"y":0.41,"z":1}],"vias":[{"x":-0.11,"y":0.1}],"rootConnectionName":"root00"},{"connectionName":"conn01","traceThickness":0.1,"viaDiameter":0.3,"route":[{"x":-0.14,"y":-0.53,"z":0},{"x":-0.04,"y":-0.43,"z":0},{"x":0.05,"y":-0.34,"z":0},{"x":0.15,"y":-0.24,"z":0},{"x":0.23,"y":-0.14,"z":0},{"x":0.28,"y":-0.03,"z":0},{"x":0.29,"y":0.1,"z":0},{"x":0.28,"y":0.22,"z":0},{"x":0.23,"y":0.34,"z":0},{"x":0.15,"y":0.43,"z":0},{"x":0.05,"y":0.53,"z":0}],"vias":[],"rootConnectionName":"root01"}],"vecRaw":[0.97,-2.93,0,0.67,1,1.48,0,-1.83,0]}
