{"capacityMeshNodeId":"sample-015143","center":{"x":0,"y":0},"width":4.5,"height":1.51,"availableZ":[0,1],"portPoints":[{"connectionName":"conn00","rootConnectionName":"root00","portPointId":"conn00-a","x":-2.26,"y":-0.5,"z":0},{"connectionName":"conn00","rootConnectionName":"root00","portPointId":"conn00-b","x":2.26,"y":-0.53,"z":0},{"connectionName":"conn01","rootConnectionName":"root01","portPointId":"conn01-a","x":0.86,"y":0.76,"z":0},{"connectionName":"conn01","rootConnectionName":"root01","portPointId":"conn01-b","x":-1.45,"y":-0.76,"z":0},{"connectionName":"conn02","rootConnectionName":"root02","portPointId":"conn02-a","x":1.26,"y":-0.76,"z":0},{"connectionName":"conn02","rootConnectionName":"root02","portPointId":"conn02-b","x":-1.22,"y":0.76,"z":0},{"connectionName":"conn03","rootConnectionName":"root03","portPointId":"conn03-a","x":0.97,"y":-0.76,"z":1},{"connectionName":"conn03","rootConnectionName":"root03","portPointId":"conn03-b","x":-0.87,"y":0.76,"z":1},{"connectionName":"conn04","rootConnectionName":"root04","portPointId":"conn04-a","x":2.26,"y":0.33,"z":0},{"connectionName":"conn04","rootConnectionName":"root04","portPointId":"conn04-b","x":0.26,"y":-0.76,"z":0},{"connectionName":"conn05","rootConnectionName":"root05","portPointId":"conn05-a","x":2.26,"y":-0.14,"z":1},{"connectionName":"conn05","rootConnectionName":"root05","portPointId":"conn05-b","x":-2.26,"y":0.41,"z":1}],"solvable":true,"solution":[{"connectionName":"conn01","traceThickness":0.1,"viaDiameter":0.3,"route":[{"x":0.92,"y":0.76,"z":0},{"x":0.7,"y":0.57,"z":0},{"x":0.5,"y":0.35,"z":0},{"x":0.31,"y":0.14,"z":0},{"x":0.06,"y":-0.02,"z":0},{"x":-0.19,"y":-0.16,"z":0},{"x":-0.47,"y":-0.21,"z":0},{"x":-0.77,"y":-0.26,"z":0},{"x":-1.03,"y":-0.35,"z":0},{"x":-1.23,"y":-0.53,"z":0},{"x":-1.43,"y":-0.76,"z":0}],"vias":[],"rootConnectionName":"root01"},{"connectionName":"conn04","traceThickness":0.1,"viaDiameter":0.3,"route":[{"x":2.25,"y":0.32,"z":0},{"x":1.98,"y":0.42,"z":0},{"x":1.72,"y":0.52,"z":0},{"x":1.45,"y":0.56,"z":0},{"x":1.18,"y":0.5,"z":0},{"x":0.95,"y":0.34,"z":0},{"x":0.72,"y":0.12,"z":0},{"x":0.51,"y":-0.1,"z":0},{"x":0.32,"y":-0.3,"z":0},{"x":0.2,"y":-0.55,"z":0},{"x":0.31,"y":-0.76,"z":0}],"vias":[],"rootConnectionName":"root04"},{"connectionName":"conn02","traceThickness":0.1,"viaDiameter":0.3,"route":[{"x":1.33,"y":-0.76,"z":0},{"x":1.38,"y":-0.66,"z":0},{"x":1.54,"y":-0.66,"z":0},{"x":1.54,"y":-0.66,"z":1},{"x":0.97,"y":0.09,"z":1},{"x":0.58,"y":0.08,"z":1},{"x":0.23,"y":0.04,"z":1},{"x":-0.11,"y":0.16,"z":1},{"x":-0.52,"y":0.69,"z":1},{"x":-0.52,"y":0.69,"z":0},{"x":-0.71,"y":0.62,"z":0},{"x":-0.99,"y":0.63,"z":0},{"x":-1.23,"y":0.76,"z":0}],"vias":[{"x":1.54,"y":-0.66},{"x":-0.52,"y":0.69}],"rootConnectionName":"root02"},{"connectionName":"conn05","traceThickness":0.1,"viaDiameter":0.3,"route":[{"x":2.25,"y":-0.11,"z":1},{"x":1.89,"y":0.33,"z":1},{"x":1.36,"y":0.48,"z":1},{"x":0.73,"y":0.56,"z":1},{"x":0.12,"y":0.52,"z":1},{"x":0.12,"y":0.52,"z":0},{"x":-0.33,"y":0.34,"z":0},{"x":-0.74,"y":0.18,"z":0},{"x":-1.14,"y":0.24,"z":0},{"x":-1.53,"y":0.43,"z":0},{"x":-1.53,"y":0.43,"z":1},{"x":-1.92,"y":0.56,"z":1},{"x":-2.25,"y":0.43,"z":1}],"vias":[{"x":0.12,"y":0.52},{"x":-1.53,"y":0.43}],"rootConnectionName":"root05"},{"connectionName":"conn00","traceThickness":0.1,"viaDiameter":0.3,"route":[{"x":-2.25,"y":-0.54,"z":0},{"x":-2.04,"y":-0.61,"z":0},{"x":-1.79,"y":-0.51,"z":0},{"x":-1.79,"y":-0.51,"z":1},{"x":-1.48,"y":-0.51,"z":1},{"x":-0.9,"y":-0.65,"z":1},{"x":-0.34,"y":-0.68,"z":1},{"x":0.19,"y":-0.67,"z":1},{"x":0.67,"y":-0.57,"z":1},{"x":0.67,"y":-0.57,"z":0},{"x":1.46,"y":-0.14,"z":0},{"x":1.82,"y":-0.36,"z":0},{"x":2.25,"y":-0.54,"z":0}],"vias":[{"x":-1.79,"y":-0.51},{"x":0.67,"y":-0.57}],"rootConnectionName":"root00"},{"connectionName":"conn03","traceThickness":0.1,"viaDiameter":0.3,"route":[{"x":1.02,"y":-0.76,"z":1},{"x":1.14,"y":-0.6,"z":1},{"x":0.9,"y":-0.16,"z":1},{"x":0.53,"y":-0.17,"z":1},{"x":0.24,"y":-0.37,"z":1},{"x":-0.04,"y":-0.35,"z":1},{"x":-0.3,"y":-0.18,"z":1},{"x":-0.53,"y":0.03,"z":1},{"x":-0.76,"y":0.23,"z":1},{"x":-0.93,"y":0.48,"z":1},{"x":-0.92,"y":0.76,"z":1}],"vias":[],"rootConnectionName":"root03"}],"vecRaw":[2.98,-2.92,-0.23,0.72,-2.66,-0.54,2.58,-0.66,2.42,0.14,-1.24,-0.06,2.96]}
